django_flags-5.0.14.dist-info/licenses/LICENSE
flags/__init__.py
flags/admin.py
flags/apps.py
flags/checks.py
flags/decorators.py
flags/forms.py
flags/jinja2tags.py
flags/middleware.py
flags/models.py
flags/panels.py
flags/sources.py
flags/state.py
flags/urls.py
flags/utils.py
flags/views.py
flags/conditions/__init__.py
flags/conditions/conditions.py
flags/conditions/registry.py
flags/conditions/validators.py
flags/management/__init__.py
flags/management/commands/__init__.py
flags/management/commands/disable_flag.py
flags/management/commands/enable_flag.py
flags/migrations/0012_replace_migrations_for_wagtail_independence.py
flags/migrations/0013_add_required_field.py
flags/migrations/__init__.py
flags/templates/flags/panels/flag_checks.html
flags/templates/flags/panels/flags.html
flags/templatetags/__init__.py
flags/templatetags/feature_flags.py
flags/templatetags/flags_debug.py
flags/tests/__init__.py
flags/tests/settings.py
flags/tests/test_admin.py
flags/tests/test_checks.py
flags/tests/test_conditions_conditions.py
flags/tests/test_conditions_registry.py
flags/tests/test_conditions_validators.py
flags/tests/test_decorators.py
flags/tests/test_forms.py
flags/tests/test_jinja2tags.py
flags/tests/test_management_commands_disable_flag.py
flags/tests/test_management_commands_enable_flag.py
flags/tests/test_middleware.py
flags/tests/test_models.py
flags/tests/test_panels.py
flags/tests/test_sources.py
flags/tests/test_state.py
flags/tests/test_templatetags_feature_flags.py
flags/tests/test_templatetags_flags_debug.py
flags/tests/test_urls.py
flags/tests/test_views.py
flags/tests/testapp/__init__.py
flags/tests/testapp/apps.py
flags/tests/testapp/models.py
flags/tests/testapp/migrations/0001_initial.py
flags/tests/testapp/migrations/__init__.py
django_flags-5.0.14.dist-info/METADATA
django_flags-5.0.14.dist-info/WHEEL
django_flags-5.0.14.dist-info/top_level.txt
django_flags-5.0.14.dist-info/RECORD
