Metadata-Version: 2.4
Name: django-flags
Version: 5.0.14
Summary: Feature flags for Django projects
Author-email: CFPB <tech@cfpb.gov>
License: CC0
Project-URL: Homepage, https://cfpb.github.io/django-flags/
Project-URL: Bug Reports, https://github.com/cfpb/django-flags/issues
Project-URL: Source, https://github.com/cfpb/django-flags
Classifier: Framework :: Django
Classifier: Framework :: Django :: 4.2
Classifier: Framework :: Django :: 5.1
Classifier: Framework :: Django :: 5.2
Classifier: License :: CC0 1.0 Universal (CC0 1.0) Public Domain Dedication
Classifier: License :: Public Domain
Classifier: Programming Language :: Python
Classifier: Programming Language :: Python :: 3
Classifier: Programming Language :: Python :: 3.8
Classifier: Programming Language :: Python :: 3.9
Classifier: Programming Language :: Python :: 3.10
Classifier: Programming Language :: Python :: 3.11
Classifier: Programming Language :: Python :: 3.12
Classifier: Programming Language :: Python :: 3.13
Requires-Python: >=3.8
License-File: LICENSE
Requires-Dist: django>=4.2
Provides-Extra: testing
Requires-Dist: coverage[toml]; extra == "testing"
Requires-Dist: django-debug-toolbar; extra == "testing"
Requires-Dist: jinja2; extra == "testing"
Provides-Extra: docs
Requires-Dist: mkdocs>=0.17; extra == "docs"
Requires-Dist: mkdocs-rtd-dropdown>=0.0.11; extra == "docs"
Requires-Dist: pymdown-extensions>=4.11; extra == "docs"
Dynamic: license-file
